README.rst
setup.py
hyiter/__init__.py
hyiter/core.hy
hyiter.egg-info/PKG-INFO
hyiter.egg-info/SOURCES.txt
hyiter.egg-info/dependency_links.txt
hyiter.egg-info/requires.txt
hyiter.egg-info/top_level.txt