Metadata-Version: 1.1
Name: hyiter
Version: 0.0.3.5
Summary: hyiter : iterate macros for hylang. inspired by https://common-lisp.net/project/iterate/
Home-page: https://github.com/riktor/hyiter/
Author: Riku Togashi
Author-email: riktor1221@gmail.com
License: MIT License
Keywords: hy lisp common-lisp
Platform: any
Classifier: License :: OSI Approved :: MIT License
Classifier: Operating System :: OS Independent
Classifier: Programming Language :: Python :: 3.4
Classifier: Programming Language :: Python :: 3.5
Classifier: Programming Language :: Python :: 3.6
